gptquery/__init__.py
gptquery/composer.py
gptquery/datatypes.py
gptquery/gpt.py
gptquery/logger.py
gptquery/pipelines.py
gptquery/utils.py
gptquery-0.0.1.dist-info/METADATA
gptquery-0.0.1.dist-info/WHEEL
gptquery-0.0.1.dist-info/top_level.txt
gptquery-0.0.1.dist-info/RECORD
